starsol_mongo_migrate/__init__.py
starsol_mongo_migrate/base.py
starsol_mongo_migrate/cli.py
starsol_mongo_migrate/db.py
starsol_mongo_migrate/manager.py
starsol_mongo_migrate/migration_path.py
starsol_mongo_migrate/template.py
starsol_mongo_migrate-0.2.0.dist-info/LICENSE
starsol_mongo_migrate-0.2.0.dist-info/METADATA
starsol_mongo_migrate-0.2.0.dist-info/WHEEL
starsol_mongo_migrate-0.2.0.dist-info/RECORD
