Metadata-Version: 2.3
Name: starsol-mongo-migrate
Version: 0.2.0
Summary: MongoDB migration tool
Keywords: starsol
Author: StarSoultion Dev Team
Author-email: dev@starsolution.team
Requires-Python: >=3.11,<4.0
Classifier: License :: OSI Approved :: MIT License
Classifier: Development Status :: 5 - Production/Stable
Classifier: Programming Language :: Python :: 3.11
Classifier: Programming Language :: Python :: 3.12
Classifier: Topic :: Software Development :: Libraries :: Python Modules
Classifier: Topic :: Database
Requires-Dist: pymongo
